llm_director/__init__.py
llm_director/base/blocks.py
llm_director/base/director.py
llm_director/test.py
llm_director/testing.ipynb
llm_director/utils/director_utils.py
llm_director-0.1.0.dist-info/LICENSE
llm_director-0.1.0.dist-info/METADATA
llm_director-0.1.0.dist-info/WHEEL
llm_director-0.1.0.dist-info/RECORD
