Metadata-Version: 2.1
Name: llm-director
Version: 0.1.0
Summary: A light-weight Python library 🐍 for deploying DAG chains of customizable Large Language Model operations. Leveraging the asyncio framework, LLM-Director allows developers to create, manage, and orchestrate actions and processes in an efficient and scalable manner. With its unique structure and integration with FastAPI, LLM-Director offes a robust solution for building applications, API endpoints, and workflow automation systems.
Author: jacob-hansen
Author-email: 85134229+jacob-hansen@users.noreply.github.com
Requires-Python: >=3.10,<4.0
Classifier: Programming Language :: Python :: 3
Classifier: Programming Language :: Python :: 3.10
Classifier: Programming Language :: Python :: 3.11
Classifier: Programming Language :: Python :: 3.12
